[{"dataSolicitacao":"203309","codigoEPI":"60014562","descricaoEPI":"CA43174 - LUVA PARA PROTECAO CONTRA AGENTES QUIMICOS TAMANHO 8 (M)","codigoMatricula":"003598","colaborador":"LUBIA LIMA DA SILVA","dataEntrega":"20231005","horaEntrega":"08:44:07","quantidadeEntregue":"3"},{"dataSolicitacao":"203309","codigoEPI":"60014561","descricaoEPI":"CA43174 - LUVA PARA PROTECAO CONTRA AGENTES QUIMICOS TAMANHO 7 (P)","codigoMatricula":"003537","colaborador":"PATRICIA BORBA DE VARGAS","dataEntrega":"20231007","horaEntrega":"09:06:51","quantidadeEntregue":"2"},{"dataSolicitacao":"203309","codigoEPI":"60014561","descricaoEPI":"CA43174 - LUVA PARA PROTECAO CONTRA AGENTES QUIMICOS TAMANHO 7 (P)","codigoMatricula":"003661","colaborador":"JENNIFER SILVA DOS SANTOS","dataEntrega":"20230902","horaEntrega":"10:40:28","quantidadeEntregue":"2"},{"dataSolicitacao":"203309","codigoEPI":"60014562","descricaoEPI":"CA43174 - LUVA PARA PROTECAO CONTRA AGENTES QUIMICOS TAMANHO 8 (M)","codigoMatricula":"003607","colaborador":"RENATA MACHADO DOS SANTOS","dataEntrega":"20231004","horaEntrega":"08:30:33","quantidadeEntregue":"3"},{"dataSolicitacao":"203309","codigoEPI":"60014561","descricaoEPI":"CA43174 - LUVA PARA PROTECAO CONTRA AGENTES QUIMICOS TAMANHO 7 (P)","codigoMatricula":"002731","colaborador":"TALITA KOHLS KLUMB GUILHERME","dataEntrega":"20231005","horaEntrega":"07:42:37","quantidadeEntregue":"3"},{"dataSolicitacao":"203309","codigoEPI":"60014561","descricaoEPI":"CA43174 - LUVA PARA PROTECAO CONTRA AGENTES QUIMICOS TAMANHO 7 (P)","codigoMatricula":"003546","colaborador":"FRANCIELE DA SILVEIRA GOETZKE LEDEBUHR","dataEntrega":"20231004","horaEntrega":"14:22:17","quantidadeEntregue":"2"},{"dataSolicitacao":"203309","codigoEPI":"60014562","descricaoEPI":"CA43174 - LUVA PARA PROTECAO CONTRA AGENTES QUIMICOS TAMANHO 8 (M)","codigoMatricula":"003524","colaborador":"VITORIA OLIVEIRA FREITAS","dataEntrega":"20231005","horaEntrega":"08:43:40","quantidadeEntregue":"3"},{"dataSolicitacao":"203309","codigoEPI":"60014561","descricaoEPI":"CA43174 - LUVA PARA PROTECAO CONTRA AGENTES QUIMICOS TAMANHO 7 (P)","codigoMatricula":"002980","colaborador":"EDUARDA VICENTINE CARDOSO","dataEntrega":"20231004","horaEntrega":"11:55:51","quantidadeEntregue":"3"},{"dataSolicitacao":"203309","codigoEPI":"60014561","descricaoEPI":"CA43174 - LUVA PARA PROTECAO CONTRA AGENTES QUIMICOS TAMANHO 7 (P)","codigoMatricula":"003564","colaborador":"KARINA FURTADO RADMANN","dataEntrega":"20231005","horaEntrega":"14:23:30","quantidadeEntregue":"3"},{"dataSolicitacao":"203309","codigoEPI":"60014561","descricaoEPI":"CA43174 - LUVA PARA PROTECAO CONTRA AGENTES QUIMICOS TAMANHO 7 (P)","codigoMatricula":"003666","colaborador":"VIVIANA CARDOSO DIETRICH","dataEntrega":"20231003","horaEntrega":"08:42:43","quantidadeEntregue":"3"},{"dataSolicitacao":"203309","codigoEPI":"60014561","descricaoEPI":"CA43174 - LUVA PARA PROTECAO CONTRA AGENTES QUIMICOS TAMANHO 7 (P)","codigoMatricula":"003530","colaborador":"KETLYN ROSARIO LEAL","dataEntrega":"20231005","horaEntrega":"12:22:03","quantidadeEntregue":"1"},{"dataSolicitacao":"203309","codigoEPI":"60014561","descricaoEPI":"CA43174 - LUVA PARA PROTECAO CONTRA AGENTES QUIMICOS TAMANHO 7 (P)","codigoMatricula":"003535","colaborador":"MAIRA HILIAN LOPES","dataEntrega":"20230928","horaEntrega":"08:01:33","quantidadeEntregue":"2"},{"dataSolicitacao":"203309","codigoEPI":"60014562","descricaoEPI":"CA43174 - LUVA PARA PROTECAO CONTRA AGENTES QUIMICOS TAMANHO 8 (M)","codigoMatricula":"003008","colaborador":"CATIA REGINA SANTOS DE SOUZA","dataEntrega":"20231005","horaEntrega":"07:49:10","quantidadeEntregue":"3"},{"dataSolicitacao":"203309","codigoEPI":"60014561","descricaoEPI":"CA43174 - LUVA PARA PROTECAO CONTRA AGENTES QUIMICOS TAMANHO 7 (P)","codigoMatricula":"003528","colaborador":"EMILLY MULLER DE ALMEIDA","dataEntrega":"20231004","horaEntrega":"08:44:13","quantidadeEntregue":"6"},{"dataSolicitacao":"203309","codigoEPI":"60014561","descricaoEPI":"CA43174 - LUVA PARA PROTECAO CONTRA AGENTES QUIMICOS TAMANHO 7 (P)","codigoMatricula":"002575","colaborador":"ANA PAULA DE MELO ISLABAO","dataEntrega":"20231003","horaEntrega":"07:59:52","quantidadeEntregue":"3"},{"dataSolicitacao":"203309","codigoEPI":"60014561","descricaoEPI":"CA43174 - LUVA PARA PROTECAO CONTRA AGENTES QUIMICOS TAMANHO 7 (P)","codigoMatricula":"003569","colaborador":"CATIA MOREIRA FELIX","dataEntrega":"20231004","horaEntrega":"08:44:52","quantidadeEntregue":"3"},{"dataSolicitacao":"203309","codigoEPI":"60014562","descricaoEPI":"CA43174 - LUVA PARA PROTECAO CONTRA AGENTES QUIMICOS TAMANHO 8 (M)","codigoMatricula":"002609","colaborador":"SIMONE CASTRO DOS SANTOS SOARES","dataEntrega":"20231004","horaEntrega":"13:01:39","quantidadeEntregue":"3"},{"dataSolicitacao":"203309","codigoEPI":"60014561","descricaoEPI":"CA43174 - LUVA PARA PROTECAO CONTRA AGENTES QUIMICOS TAMANHO 7 (P)","codigoMatricula":"003601","colaborador":"TOCHIE KIMURA","dataEntrega":"20231005","horaEntrega":"07:41:42","quantidadeEntregue":"1"},{"dataSolicitacao":"203309","codigoEPI":"60014561","descricaoEPI":"CA43174 - LUVA PARA PROTECAO CONTRA AGENTES QUIMICOS TAMANHO 7 (P)","codigoMatricula":"003034","colaborador":"VANESSA FERNADES MACHADO","dataEntrega":"20231005","horaEntrega":"11:35:22","quantidadeEntregue":"2"},{"dataSolicitacao":"203309","codigoEPI":"60014561","descricaoEPI":"CA43174 - LUVA PARA PROTECAO CONTRA AGENTES QUIMICOS TAMANHO 7 (P)","codigoMatricula":"003605","colaborador":"MAYNARA BREDOW DOS SANTOS","dataEntrega":"20231003","horaEntrega":"12:23:13","quantidadeEntregue":"1"},{"dataSolicitacao":"203309","codigoEPI":"60014561","descricaoEPI":"CA43174 - LUVA PARA PROTECAO CONTRA AGENTES QUIMICOS TAMANHO 7 (P)","codigoMatricula":"003643","colaborador":"KAYLANE SOUZA BENTO","dataEntrega":"20231005","horaEntrega":"14:16:31","quantidadeEntregue":"2"},{"dataSolicitacao":"203309","codigoEPI":"60014561","descricaoEPI":"CA43174 - LUVA PARA PROTECAO CONTRA AGENTES QUIMICOS TAMANHO 7 (P)","codigoMatricula":"003589","colaborador":"KEROLAINE MORAES FERREIRA","dataEntrega":"20231003","horaEntrega":"11:09:47","quantidadeEntregue":"3"},{"dataSolicitacao":"203309","codigoEPI":"60014561","descricaoEPI":"CA43174 - LUVA PARA PROTECAO CONTRA AGENTES QUIMICOS TAMANHO 7 (P)","codigoMatricula":"003522","colaborador":"CLAUDIANA OLIVEIRA","dataEntrega":"20231005","horaEntrega":"08:40:05","quantidadeEntregue":"5"},{"dataSolicitacao":"203309","codigoEPI":"60014562","descricaoEPI":"CA43174 - LUVA PARA PROTECAO CONTRA AGENTES QUIMICOS TAMANHO 8 (M)","codigoMatricula":"002655","colaborador":"CAROLINE SILVEIRA MATOZO","dataEntrega":"20231004","horaEntrega":"07:39:33","quantidadeEntregue":"2"},{"dataSolicitacao":"203309","codigoEPI":"60014561","descricaoEPI":"CA43174 - LUVA PARA PROTECAO CONTRA AGENTES QUIMICOS TAMANHO 7 (P)","codigoMatricula":"003663","colaborador":"EDILAINE ULGUIM DILLMANN","dataEntrega":"20231005","horaEntrega":"13:01:28","quantidadeEntregue":"3"},{"dataSolicitacao":"203309","codigoEPI":"60014562","descricaoEPI":"CA43174 - LUVA PARA PROTECAO CONTRA AGENTES QUIMICOS TAMANHO 8 (M)","codigoMatricula":"003036","colaborador":"CATIUSCIA MATIAS MENEGONI","dataEntrega":"20230926","horaEntrega":"20:18:40","quantidadeEntregue":"3"},{"dataSolicitacao":"203309","codigoEPI":"60014561","descricaoEPI":"CA43174 - LUVA PARA PROTECAO CONTRA AGENTES QUIMICOS TAMANHO 7 (P)","codigoMatricula":"003552","colaborador":"ELISANGELA RODRIGUES CARDOSO","dataEntrega":"20231005","horaEntrega":"13:00:52","quantidadeEntregue":"3"},{"dataSolicitacao":"203309","codigoEPI":"60014563","descricaoEPI":"CA43174 - LUVA PARA PROTECAO CONTRA AGENTES QUIMICOS TAMANHO 9 (G)","codigoMatricula":"003406","colaborador":"ELIANE VIEIRA PINHEIRO","dataEntrega":"20231005","horaEntrega":"07:15:07","quantidadeEntregue":"3"},{"dataSolicitacao":"203309","codigoEPI":"60014562","descricaoEPI":"CA43174 - LUVA PARA PROTECAO CONTRA AGENTES QUIMICOS TAMANHO 8 (M)","codigoMatricula":"003660","colaborador":"ANGELA MARIA WULFF","dataEntrega":"20231004","horaEntrega":"13:03:11","quantidadeEntregue":"4"},{"dataSolicitacao":"203309","codigoEPI":"60014561","descricaoEPI":"CA43174 - LUVA PARA PROTECAO CONTRA AGENTES QUIMICOS TAMANHO 7 (P)","codigoMatricula":"003527","colaborador":"CHARLENE SARAIVA LOPES","dataEntrega":"20231003","horaEntrega":"08:45:15","quantidadeEntregue":"4"},{"dataSolicitacao":"203309","codigoEPI":"60014561","descricaoEPI":"CA43174 - LUVA PARA PROTECAO CONTRA AGENTES QUIMICOS TAMANHO 7 (P)","codigoMatricula":"003591","colaborador":"TAUANA LACERDA EINHARDT","dataEntrega":"20231004","horaEntrega":"11:07:56","quantidadeEntregue":"1"},{"dataSolicitacao":"203309","codigoEPI":"60014561","descricaoEPI":"CA43174 - LUVA PARA PROTECAO CONTRA AGENTES QUIMICOS TAMANHO 7 (P)","codigoMatricula":"002644","colaborador":"BRUNA SCHAUN THEIS","dataEntrega":"20231005","horaEntrega":"14:14:36","quantidadeEntregue":"4"},{"dataSolicitacao":"203309","codigoEPI":"60014561","descricaoEPI":"CA43174 - LUVA PARA PROTECAO CONTRA AGENTES QUIMICOS TAMANHO 7 (P)","codigoMatricula":"002710","colaborador":"PRISCILA BAAD BUDZIARECK","dataEntrega":"20231005","horaEntrega":"14:08:31","quantidadeEntregue":"3"},{"dataSolicitacao":"203309","codigoEPI":"60014561","descricaoEPI":"CA43174 - LUVA PARA PROTECAO CONTRA AGENTES QUIMICOS TAMANHO 7 (P)","codigoMatricula":"002090","colaborador":"SANDRA MADALENA SEVERO CARDOSO","dataEntrega":"20231005","horaEntrega":"11:43:40","quantidadeEntregue":"2"},{"dataSolicitacao":"203309","codigoEPI":"60014561","descricaoEPI":"CA43174 - LUVA PARA PROTECAO CONTRA AGENTES QUIMICOS TAMANHO 7 (P)","codigoMatricula":"002877","colaborador":"VANESSA GOUVEA DE OLIVEIRA","dataEntrega":"20231004","horaEntrega":"14:04:26","quantidadeEntregue":"1"},{"dataSolicitacao":"203309","codigoEPI":"60014561","descricaoEPI":"CA43174 - LUVA PARA PROTECAO CONTRA AGENTES QUIMICOS TAMANHO 7 (P)","codigoMatricula":"003567","colaborador":"ANDRESSA DA SILVA BARBOSA","dataEntrega":"20230930","horaEntrega":"14:41:31","quantidadeEntregue":"3"},{"dataSolicitacao":"203309","codigoEPI":"60014562","descricaoEPI":"CA43174 - LUVA PARA PROTECAO CONTRA AGENTES QUIMICOS TAMANHO 8 (M)","codigoMatricula":"003237","colaborador":"RAQUEL VILELLA FARIAS","dataEntrega":"20231005","horaEntrega":"07:04:08","quantidadeEntregue":"3"},{"dataSolicitacao":"203309","codigoEPI":"60014561","descricaoEPI":"CA43174 - LUVA PARA PROTECAO CONTRA AGENTES QUIMICOS TAMANHO 7 (P)","codigoMatricula":"003667","colaborador":"ALINE DA SILVA MACHADO","dataEntrega":"20231004","horaEntrega":"14:13:53","quantidadeEntregue":"3"},{"dataSolicitacao":"203309","codigoEPI":"60014561","descricaoEPI":"CA43174 - LUVA PARA PROTECAO CONTRA AGENTES QUIMICOS TAMANHO 7 (P)","codigoMatricula":"003374","colaborador":"VALESCA RODRIGUES DIAS","dataEntrega":"20231003","horaEntrega":"14:01:37","quantidadeEntregue":"3"},{"dataSolicitacao":"203309","codigoEPI":"60014562","descricaoEPI":"CA43174 - LUVA PARA PROTECAO CONTRA AGENTES QUIMICOS TAMANHO 8 (M)","codigoMatricula":"003263","colaborador":"LEDIANE RODRIGUES CARDOSO","dataEntrega":"20231005","horaEntrega":"12:26:19","quantidadeEntregue":"3"},{"dataSolicitacao":"203309","codigoEPI":"60014561","descricaoEPI":"CA43174 - LUVA PARA PROTECAO CONTRA AGENTES QUIMICOS TAMANHO 7 (P)","codigoMatricula":"002733","colaborador":"PRISCILA NUNES RODRIGUES","dataEntrega":"20231003","horaEntrega":"08:08:01","quantidadeEntregue":"3"},{"dataSolicitacao":"203309","codigoEPI":"60014561","descricaoEPI":"CA43174 - LUVA PARA PROTECAO CONTRA AGENTES QUIMICOS TAMANHO 7 (P)","codigoMatricula":"003241","colaborador":"SHAUANNY CARDOSO TAVARES","dataEntrega":"20230916","horaEntrega":"10:38:14","quantidadeEntregue":"3"},{"dataSolicitacao":"203309","codigoEPI":"60014562","descricaoEPI":"CA43174 - LUVA PARA PROTECAO CONTRA AGENTES QUIMICOS TAMANHO 8 (M)","codigoMatricula":"003540","colaborador":"LEONARDO DAMASCENO DOS SANTOS","dataEntrega":"20231004","horaEntrega":"11:06:35","quantidadeEntregue":"4"},{"dataSolicitacao":"203309","codigoEPI":"60014561","descricaoEPI":"CA43174 - LUVA PARA PROTECAO CONTRA AGENTES QUIMICOS TAMANHO 7 (P)","codigoMatricula":"003651","colaborador":"NATIELE DOS SANTOS WEIKAMP","dataEntrega":"20231005","horaEntrega":"14:19:05","quantidadeEntregue":"2"},{"dataSolicitacao":"203309","codigoEPI":"60014561","descricaoEPI":"CA43174 - LUVA PARA PROTECAO CONTRA AGENTES QUIMICOS TAMANHO 7 (P)","codigoMatricula":"003647","colaborador":"FRANCIELE ROCHA SILVEIRA","dataEntrega":"20231005","horaEntrega":"14:24:03","quantidadeEntregue":"3"},{"dataSolicitacao":"203309","codigoEPI":"60014561","descricaoEPI":"CA43174 - LUVA PARA PROTECAO CONTRA AGENTES QUIMICOS TAMANHO 7 (P)","codigoMatricula":"003674","colaborador":"EDUARDA DA SILVA XAVIER","dataEntrega":"20231007","horaEntrega":"09:08:08","quantidadeEntregue":"3"},{"dataSolicitacao":"203309","codigoEPI":"60014561","descricaoEPI":"CA43174 - LUVA PARA PROTECAO CONTRA AGENTES QUIMICOS TAMANHO 7 (P)","codigoMatricula":"003547","colaborador":"DIULIENE FREITAS DOS SANTOS","dataEntrega":"20231005","horaEntrega":"14:25:10","quantidadeEntregue":"1"},{"dataSolicitacao":"203309","codigoEPI":"60014561","descricaoEPI":"CA43174 - LUVA PARA PROTECAO CONTRA AGENTES QUIMICOS TAMANHO 7 (P)","codigoMatricula":"002730","colaborador":"RITIELE SEVERO NUNES","dataEntrega":"20231003","horaEntrega":"14:20:10","quantidadeEntregue":"2"},{"dataSolicitacao":"203309","codigoEPI":"60014562","descricaoEPI":"CA43174 - LUVA PARA PROTECAO CONTRA AGENTES QUIMICOS TAMANHO 8 (M)","codigoMatricula":"003641","colaborador":"BRUNA NUNES LESSA","dataEntrega":"20231005","horaEntrega":"11:40:18","quantidadeEntregue":"3"},{"dataSolicitacao":"2043","codigoEPI":"60014562","descricaoEPI":"CA43174 - LUVA PARA PROTECAO CONTRA AGENTES QUIMICOS TAMANHO 8 (M)","codigoMatricula":"002687","colaborador":"CAROLINA KIRST LOPES","dataEntrega":"20231004","horaEntrega":"13:57:29","quantidadeEntregue":"5"},{"dataSolicitacao":"2043","codigoEPI":"60014562","descricaoEPI":"CA43174 - LUVA PARA PROTECAO CONTRA AGENTES QUIMICOS TAMANHO 8 (M)","codigoMatricula":"003535","colaborador":"MAIRA HILIAN LOPES","dataEntrega":"20231005","horaEntrega":"08:43:10","quantidadeEntregue":"3"},{"dataSolicitacao":"2043","codigoEPI":"60014561","descricaoEPI":"CA43174 - LUVA PARA PROTECAO CONTRA AGENTES QUIMICOS TAMANHO 7 (P)","codigoMatricula":"003563","colaborador":"TAISCIANE TORRES NOBRE","dataEntrega":"20231003","horaEntrega":"11:32:14","quantidadeEntregue":"4"},{"dataSolicitacao":"2043","codigoEPI":"60014561","descricaoEPI":"CA43174 - LUVA PARA PROTECAO CONTRA AGENTES QUIMICOS TAMANHO 7 (P)","codigoMatricula":"003528","colaborador":"EMILLY MULLER DE ALMEIDA","dataEntrega":"20231004","horaEntrega":"08:44:13","quantidadeEntregue":"6"},{"dataSolicitacao":"2043","codigoEPI":"60014561","descricaoEPI":"CA43174 - LUVA PARA PROTECAO CONTRA AGENTES QUIMICOS TAMANHO 7 (P)","codigoMatricula":"003071","colaborador":"LETICIA DE LIMA ORTIZ","dataEntrega":"20231005","horaEntrega":"08:05:18","quantidadeEntregue":"3"},{"dataSolicitacao":"2043","codigoEPI":"60014562","descricaoEPI":"CA43174 - LUVA PARA PROTECAO CONTRA AGENTES QUIMICOS TAMANHO 8 (M)","codigoMatricula":"003524","colaborador":"VITORIA OLIVEIRA FREITAS","dataEntrega":"20231005","horaEntrega":"08:43:40","quantidadeEntregue":"3"},{"dataSolicitacao":"2043","codigoEPI":"60014562","descricaoEPI":"CA43174 - LUVA PARA PROTECAO CONTRA AGENTES QUIMICOS TAMANHO 8 (M)","codigoMatricula":"001307","colaborador":"BIANE MOTA DA SILVA","dataEntrega":"20230923","horaEntrega":"08:03:09","quantidadeEntregue":"2"},{"dataSolicitacao":"2043","codigoEPI":"60014561","descricaoEPI":"CA43174 - LUVA PARA PROTECAO CONTRA AGENTES QUIMICOS TAMANHO 7 (P)","codigoMatricula":"003663","colaborador":"EDILAINE ULGUIM DILLMANN","dataEntrega":"20231005","horaEntrega":"13:01:28","quantidadeEntregue":"3"},{"dataSolicitacao":"2043","codigoEPI":"60014561","descricaoEPI":"CA43174 - LUVA PARA PROTECAO CONTRA AGENTES QUIMICOS TAMANHO 7 (P)","codigoMatricula":"003647","colaborador":"FRANCIELE ROCHA SILVEIRA","dataEntrega":"20231005","horaEntrega":"14:24:03","quantidadeEntregue":"3"},{"dataSolicitacao":"2043","codigoEPI":"60014562","descricaoEPI":"CA43174 - LUVA PARA PROTECAO CONTRA AGENTES QUIMICOS TAMANHO 8 (M)","codigoMatricula":"003652","colaborador":"DIELE ROJAHN DOS SANTOS","dataEntrega":"20231005","horaEntrega":"12:23:08","quantidadeEntregue":"3"},{"dataSolicitacao":"2043","codigoEPI":"60014561","descricaoEPI":"CA43174 - LUVA PARA PROTECAO CONTRA AGENTES QUIMICOS TAMANHO 7 (P)","codigoMatricula":"002523","colaborador":"CRISTIANE RAMOS ALVES","dataEntrega":"20230921","horaEntrega":"06:19:40","quantidadeEntregue":"1"},{"dataSolicitacao":"2043","codigoEPI":"60014562","descricaoEPI":"CA43174 - LUVA PARA PROTECAO CONTRA AGENTES QUIMICOS TAMANHO 8 (M)","codigoMatricula":"003601","colaborador":"TOCHIE KIMURA","dataEntrega":"20230928","horaEntrega":"07:50:29","quantidadeEntregue":"1"},{"dataSolicitacao":"2043","codigoEPI":"60014561","descricaoEPI":"CA43174 - LUVA PARA PROTECAO CONTRA AGENTES QUIMICOS TAMANHO 7 (P)","codigoMatricula":"001597","colaborador":"RAQUEL NORNBERG OLIVEIRA","dataEntrega":"20231003","horaEntrega":"07:57:23","quantidadeEntregue":"3"},{"dataSolicitacao":"2043","codigoEPI":"60014561","descricaoEPI":"CA43174 - LUVA PARA PROTECAO CONTRA AGENTES QUIMICOS TAMANHO 7 (P)","codigoMatricula":"003546","colaborador":"FRANCIELE DA SILVEIRA GOETZKE LEDEBUHR","dataEntrega":"20231004","horaEntrega":"14:22:17","quantidadeEntregue":"2"},{"dataSolicitacao":"2043","codigoEPI":"60014561","descricaoEPI":"CA43174 - LUVA PARA PROTECAO CONTRA AGENTES QUIMICOS TAMANHO 7 (P)","codigoMatricula":"003552","colaborador":"ELISANGELA RODRIGUES CARDOSO","dataEntrega":"20231005","horaEntrega":"13:00:52","quantidadeEntregue":"3"},{"dataSolicitacao":"2043","codigoEPI":"60014562","descricaoEPI":"CA43174 - LUVA PARA PROTECAO CONTRA AGENTES QUIMICOS TAMANHO 8 (M)","codigoMatricula":"003598","colaborador":"LUBIA LIMA DA SILVA","dataEntrega":"20231005","horaEntrega":"08:44:07","quantidadeEntregue":"3"},{"dataSolicitacao":"2043","codigoEPI":"60014561","descricaoEPI":"CA43174 - LUVA PARA PROTECAO CONTRA AGENTES QUIMICOS TAMANHO 7 (P)","codigoMatricula":"003537","colaborador":"PATRICIA BORBA DE VARGAS","dataEntrega":"20231007","horaEntrega":"09:06:51","quantidadeEntregue":"2"},{"dataSolicitacao":"2043","codigoEPI":"60014562","descricaoEPI":"CA43174 - LUVA PARA PROTECAO CONTRA AGENTES QUIMICOS TAMANHO 8 (M)","codigoMatricula":"003661","colaborador":"JENNIFER SILVA DOS SANTOS","dataEntrega":"20231004","horaEntrega":"08:25:22","quantidadeEntregue":"3"},{"dataSolicitacao":"2043","codigoEPI":"60014561","descricaoEPI":"CA43174 - LUVA PARA PROTECAO CONTRA AGENTES QUIMICOS TAMANHO 7 (P)","codigoMatricula":"003589","colaborador":"KEROLAINE MORAES FERREIRA","dataEntrega":"20231003","horaEntrega":"11:09:47","quantidadeEntregue":"3"},{"dataSolicitacao":"2043","codigoEPI":"60014562","descricaoEPI":"CA43174 - LUVA PARA PROTECAO CONTRA AGENTES QUIMICOS TAMANHO 8 (M)","codigoMatricula":"003008","colaborador":"CATIA REGINA SANTOS DE SOUZA","dataEntrega":"20231005","horaEntrega":"07:49:10","quantidadeEntregue":"3"},{"dataSolicitacao":"2043","codigoEPI":"60014561","descricaoEPI":"CA43174 - LUVA PARA PROTECAO CONTRA AGENTES QUIMICOS TAMANHO 7 (P)","codigoMatricula":"003666","colaborador":"VIVIANA CARDOSO DIETRICH","dataEntrega":"20231003","horaEntrega":"08:42:43","quantidadeEntregue":"3"},{"dataSolicitacao":"2043","codigoEPI":"60014561","descricaoEPI":"CA43174 - LUVA PARA PROTECAO CONTRA AGENTES QUIMICOS TAMANHO 7 (P)","codigoMatricula":"003530","colaborador":"KETLYN ROSARIO LEAL","dataEntrega":"20231005","horaEntrega":"12:22:03","quantidadeEntregue":"1"},{"dataSolicitacao":"2043","codigoEPI":"60014561","descricaoEPI":"CA43174 - LUVA PARA PROTECAO CONTRA AGENTES QUIMICOS TAMANHO 7 (P)","codigoMatricula":"002644","colaborador":"BRUNA SCHAUN THEIS","dataEntrega":"20231005","horaEntrega":"14:14:36","quantidadeEntregue":"4"},{"dataSolicitacao":"2043","codigoEPI":"60014562","descricaoEPI":"CA43174 - LUVA PARA PROTECAO CONTRA AGENTES QUIMICOS TAMANHO 8 (M)","codigoMatricula":"003015","colaborador":"MIRIAN LANE PINTO DA SILVA","dataEntrega":"20231004","horaEntrega":"07:20:54","quantidadeEntregue":"3"},{"dataSolicitacao":"2043","codigoEPI":"60014561","descricaoEPI":"CA43174 - LUVA PARA PROTECAO CONTRA AGENTES QUIMICOS TAMANHO 7 (P)","codigoMatricula":"003218","colaborador":"SHEILA LACERDA EINHARDT","dataEntrega":"20231003","horaEntrega":"08:01:25","quantidadeEntregue":"3"},{"dataSolicitacao":"2043","codigoEPI":"60014561","descricaoEPI":"CA43174 - LUVA PARA PROTECAO CONTRA AGENTES QUIMICOS TAMANHO 7 (P)","codigoMatricula":"003643","colaborador":"KAYLANE SOUZA BENTO","dataEntrega":"20231005","horaEntrega":"14:16:31","quantidadeEntregue":"2"},{"dataSolicitacao":"2043","codigoEPI":"60014562","descricaoEPI":"CA43174 - LUVA PARA PROTECAO CONTRA AGENTES QUIMICOS TAMANHO 8 (M)","codigoMatricula":"003237","colaborador":"RAQUEL VILELLA FARIAS","dataEntrega":"20231005","horaEntrega":"07:04:08","quantidadeEntregue":"3"},{"dataSolicitacao":"2043","codigoEPI":"60014561","descricaoEPI":"CA43174 - LUVA PARA PROTECAO CONTRA AGENTES QUIMICOS TAMANHO 7 (P)","codigoMatricula":"002575","colaborador":"ANA PAULA DE MELO ISLABAO","dataEntrega":"20231003","horaEntrega":"07:59:52","quantidadeEntregue":"3"},{"dataSolicitacao":"2043","codigoEPI":"60014562","descricaoEPI":"CA43174 - LUVA PARA PROTECAO CONTRA AGENTES QUIMICOS TAMANHO 8 (M)","codigoMatricula":"001552","colaborador":"CELINA MARES DUARTE FAGUNDES","dataEntrega":"20230923","horaEntrega":"12:40:04","quantidadeEntregue":"2"},{"dataSolicitacao":"2043","codigoEPI":"60014561","descricaoEPI":"CA43174 - LUVA PARA PROTECAO CONTRA AGENTES QUIMICOS TAMANHO 7 (P)","codigoMatricula":"003664","colaborador":"BIANCA BORGES MARTINS","dataEntrega":"20231005","horaEntrega":"14:07:52","quantidadeEntregue":"2"},{"dataSolicitacao":"2043","codigoEPI":"60014561","descricaoEPI":"CA43174 - LUVA PARA PROTECAO CONTRA AGENTES QUIMICOS TAMANHO 7 (P)","codigoMatricula":"003602","colaborador":"ANA CAROLINA SOUZA ROSSALES","dataEntrega":"20231005","horaEntrega":"11:36:36","quantidadeEntregue":"1"},{"dataSolicitacao":"2043","codigoEPI":"60014562","descricaoEPI":"CA43174 - LUVA PARA PROTECAO CONTRA AGENTES QUIMICOS TAMANHO 8 (M)","codigoMatricula":"003036","colaborador":"CATIUSCIA MATIAS MENEGONI","dataEntrega":"20231009","horaEntrega":"12:23:09","quantidadeEntregue":"3"},{"dataSolicitacao":"2043","codigoEPI":"60014561","descricaoEPI":"CA43174 - LUVA PARA PROTECAO CONTRA AGENTES QUIMICOS TAMANHO 7 (P)","codigoMatricula":"003605","colaborador":"MAYNARA BREDOW DOS SANTOS","dataEntrega":"20231003","horaEntrega":"12:23:13","quantidadeEntregue":"1"},{"dataSolicitacao":"2043","codigoEPI":"60014562","descricaoEPI":"CA43174 - LUVA PARA PROTECAO CONTRA AGENTES QUIMICOS TAMANHO 8 (M)","codigoMatricula":"002655","colaborador":"CAROLINE SILVEIRA MATOZO","dataEntrega":"20231004","horaEntrega":"07:39:33","quantidadeEntregue":"2"},{"dataSolicitacao":"2043","codigoEPI":"60014561","descricaoEPI":"CA43174 - LUVA PARA PROTECAO CONTRA AGENTES QUIMICOS TAMANHO 7 (P)","codigoMatricula":"003591","colaborador":"TAUANA LACERDA EINHARDT","dataEntrega":"20231004","horaEntrega":"11:07:56","quantidadeEntregue":"1"},{"dataSolicitacao":"2043","codigoEPI":"60014561","descricaoEPI":"CA43174 - LUVA PARA PROTECAO CONTRA AGENTES QUIMICOS TAMANHO 7 (P)","codigoMatricula":"003594","colaborador":"MAGDA FREITAS RIBEIRO","dataEntrega":"20231005","horaEntrega":"07:50:13","quantidadeEntregue":"2"},{"dataSolicitacao":"2043","codigoEPI":"60014562","descricaoEPI":"CA43174 - LUVA PARA PROTECAO CONTRA AGENTES QUIMICOS TAMANHO 8 (M)","codigoMatricula":"001307","colaborador":"BIANE MOTA DA SILVA","dataEntrega":"20231010","horaEntrega":"08:49:01","quantidadeEntregue":"4"},{"dataSolicitacao":"2043","codigoEPI":"60014562","descricaoEPI":"CA43174 - LUVA PARA PROTECAO CONTRA AGENTES QUIMICOS TAMANHO 8 (M)","codigoMatricula":"003607","colaborador":"RENATA MACHADO DOS SANTOS","dataEntrega":"20231004","horaEntrega":"08:30:33","quantidadeEntregue":"3"},{"dataSolicitacao":"2043","codigoEPI":"60014561","descricaoEPI":"CA43174 - LUVA PARA PROTECAO CONTRA AGENTES QUIMICOS TAMANHO 7 (P)","codigoMatricula":"003374","colaborador":"VALESCA RODRIGUES DIAS","dataEntrega":"20231003","horaEntrega":"14:01:37","quantidadeEntregue":"3"},{"dataSolicitacao":"2043","codigoEPI":"60014562","descricaoEPI":"CA43174 - LUVA PARA PROTECAO CONTRA AGENTES QUIMICOS TAMANHO 8 (M)","codigoMatricula":"002609","colaborador":"SIMONE CASTRO DOS SANTOS SOARES","dataEntrega":"20231004","horaEntrega":"13:01:39","quantidadeEntregue":"3"},{"dataSolicitacao":"2043","codigoEPI":"60014562","descricaoEPI":"CA43174 - LUVA PARA PROTECAO CONTRA AGENTES QUIMICOS TAMANHO 8 (M)","codigoMatricula":"003540","colaborador":"LEONARDO DAMASCENO DOS SANTOS","dataEntrega":"20231004","horaEntrega":"11:06:35","quantidadeEntregue":"4"},{"dataSolicitacao":"2043","codigoEPI":"60014561","descricaoEPI":"CA43174 - LUVA PARA PROTECAO CONTRA AGENTES QUIMICOS TAMANHO 7 (P)","codigoMatricula":"002714","colaborador":"ANDIARA SCHMIELE DE OLIVEIRA","dataEntrega":"20231004","horaEntrega":"14:02:28","quantidadeEntregue":"1"},{"dataSolicitacao":"2043","codigoEPI":"60014561","descricaoEPI":"CA43174 - LUVA PARA PROTECAO CONTRA AGENTES QUIMICOS TAMANHO 7 (P)","codigoMatricula":"002877","colaborador":"VANESSA GOUVEA DE OLIVEIRA","dataEntrega":"20231004","horaEntrega":"14:04:26","quantidadeEntregue":"1"},{"dataSolicitacao":"2043","codigoEPI":"60014561","descricaoEPI":"CA43174 - LUVA PARA PROTECAO CONTRA AGENTES QUIMICOS TAMANHO 7 (P)","codigoMatricula":"002730","colaborador":"RITIELE SEVERO NUNES","dataEntrega":"20231003","horaEntrega":"14:20:10","quantidadeEntregue":"2"},{"dataSolicitacao":"2043","codigoEPI":"60014561","descricaoEPI":"CA43174 - LUVA PARA PROTECAO CONTRA AGENTES QUIMICOS TAMANHO 7 (P)","codigoMatricula":"002733","colaborador":"PRISCILA NUNES RODRIGUES","dataEntrega":"20231003","horaEntrega":"08:08:01","quantidadeEntregue":"3"},{"dataSolicitacao":"2043","codigoEPI":"60014561","descricaoEPI":"CA43174 - LUVA PARA PROTECAO CONTRA AGENTES QUIMICOS TAMANHO 7 (P)","codigoMatricula":"002710","colaborador":"PRISCILA BAAD BUDZIARECK","dataEntrega":"20231005","horaEntrega":"14:08:31","quantidadeEntregue":"3"},{"dataSolicitacao":"2043","codigoEPI":"60014561","descricaoEPI":"CA43174 - LUVA PARA PROTECAO CONTRA AGENTES QUIMICOS TAMANHO 7 (P)","codigoMatricula":"003252","colaborador":"THAIS NUNES DUARTE","dataEntrega":"20231003","horaEntrega":"14:19:34","quantidadeEntregue":"3"},{"dataSolicitacao":"2043","codigoEPI":"60014562","descricaoEPI":"CA43174 - LUVA PARA PROTECAO CONTRA AGENTES QUIMICOS TAMANHO 8 (M)","codigoMatricula":"002510","colaborador":"LUCIANA DA SILVA SOARES","dataEntrega":"20230921","horaEntrega":"22:47:56","quantidadeEntregue":"1"},{"dataSolicitacao":"2043","codigoEPI":"60014561","descricaoEPI":"CA43174 - LUVA PARA PROTECAO CONTRA AGENTES QUIMICOS TAMANHO 7 (P)","codigoMatricula":"003667","colaborador":"ALINE DA SILVA MACHADO","dataEntrega":"20231004","horaEntrega":"14:13:53","quantidadeEntregue":"3"},{"dataSolicitacao":"2043","codigoEPI":"60014562","descricaoEPI":"CA43174 - LUVA PARA PROTECAO CONTRA AGENTES QUIMICOS TAMANHO 8 (M)","codigoMatricula":"003592","colaborador":"ALINE DOS SANTOS VEIGA","dataEntrega":"20231005","horaEntrega":"14:23:00","quantidadeEntregue":"3"},{"dataSolicitacao":"2043","codigoEPI":"60014561","descricaoEPI":"CA43174 - LUVA PARA PROTECAO CONTRA AGENTES QUIMICOS TAMANHO 7 (P)","codigoMatricula":"003656","colaborador":"RAQUEL OLIVEIRA M DA SILVA","dataEntrega":"20231005","horaEntrega":"14:20:17","quantidadeEntregue":"3"},{"dataSolicitacao":"2043","codigoEPI":"60014562","descricaoEPI":"CA43174 - LUVA PARA PROTECAO CONTRA AGENTES QUIMICOS TAMANHO 8 (M)","codigoMatricula":"003650","colaborador":"SAMANTHA COLVARA ESMERIO","dataEntrega":"20231005","horaEntrega":"14:17:42","quantidadeEntregue":"3"},{"dataSolicitacao":"2043","codigoEPI":"60014562","descricaoEPI":"CA43174 - LUVA PARA PROTECAO CONTRA AGENTES QUIMICOS TAMANHO 8 (M)","codigoMatricula":"003263","colaborador":"LEDIANE RODRIGUES CARDOSO","dataEntrega":"20231005","horaEntrega":"12:26:19","quantidadeEntregue":"3"},{"dataSolicitacao":"2043","codigoEPI":"60014561","descricaoEPI":"CA43174 - LUVA PARA PROTECAO CONTRA AGENTES QUIMICOS TAMANHO 7 (P)","codigoMatricula":"003527","colaborador":"CHARLENE SARAIVA LOPES","dataEntrega":"20231003","horaEntrega":"08:45:15","quantidadeEntregue":"4"},{"dataSolicitacao":"2043","codigoEPI":"60014562","descricaoEPI":"CA43174 - LUVA PARA PROTECAO CONTRA AGENTES QUIMICOS TAMANHO 8 (M)","codigoMatricula":"001993","colaborador":"CATARINA PORTO SOUZA","dataEntrega":"20230922","horaEntrega":"23:11:21","quantidadeEntregue":"3"},{"dataSolicitacao":"2043","codigoEPI":"60014561","descricaoEPI":"CA43174 - LUVA PARA PROTECAO CONTRA AGENTES QUIMICOS TAMANHO 7 (P)","codigoMatricula":"002973","colaborador":"ELIANE PINTO AIRES NEITZKE","dataEntrega":"20231005","horaEntrega":"14:19:37","quantidadeEntregue":"3"},{"dataSolicitacao":"2043","codigoEPI":"60014561","descricaoEPI":"CA43174 - LUVA PARA PROTECAO CONTRA AGENTES QUIMICOS TAMANHO 7 (P)","codigoMatricula":"003547","colaborador":"DIULIENE FREITAS DOS SANTOS","dataEntrega":"20231005","horaEntrega":"14:25:10","quantidadeEntregue":"1"},{"dataSolicitacao":"2044","codigoEPI":"60014561","descricaoEPI":"CA43174 - LUVA PARA PROTECAO CONTRA AGENTES QUIMICOS TAMANHO 7 (P)","codigoMatricula":"003569","colaborador":"CATIA MOREIRA FELIX","dataEntrega":"20231004","horaEntrega":"08:44:52","quantidadeEntregue":"3"},{"dataSolicitacao":"2044","codigoEPI":"60014561","descricaoEPI":"CA43174 - LUVA PARA PROTECAO CONTRA AGENTES QUIMICOS TAMANHO 7 (P)","codigoMatricula":"003679","colaborador":"LUIZA AGUIAR DA SILVA","dataEntrega":"20231004","horaEntrega":"13:04:13","quantidadeEntregue":"4"},{"dataSolicitacao":"2044","codigoEPI":"60014561","descricaoEPI":"CA43174 - LUVA PARA PROTECAO CONTRA AGENTES QUIMICOS TAMANHO 7 (P)","codigoMatricula":"003071","colaborador":"LETICIA DE LIMA ORTIZ","dataEntrega":"20231005","horaEntrega":"08:05:18","quantidadeEntregue":"3"},{"dataSolicitacao":"2044","codigoEPI":"60014562","descricaoEPI":"CA43174 - LUVA PARA PROTECAO CONTRA AGENTES QUIMICOS TAMANHO 8 (M)","codigoMatricula":"003543","colaborador":"BRENDA LARISSA FUCOLO MOURA","dataEntrega":"20231005","horaEntrega":"12:15:29","quantidadeEntregue":"4"},{"dataSolicitacao":"2044","codigoEPI":"60014561","descricaoEPI":"CA43174 - LUVA PARA PROTECAO CONTRA AGENTES QUIMICOS TAMANHO 7 (P)","codigoMatricula":"003552","colaborador":"ELISANGELA RODRIGUES CARDOSO","dataEntrega":"20231005","horaEntrega":"13:00:52","quantidadeEntregue":"3"},{"dataSolicitacao":"2044","codigoEPI":"60014561","descricaoEPI":"CA43174 - LUVA PARA PROTECAO CONTRA AGENTES QUIMICOS TAMANHO 7 (P)","codigoMatricula":"002973","colaborador":"ELIANE PINTO AIRES NEITZKE","dataEntrega":"20231005","horaEntrega":"14:19:37","quantidadeEntregue":"3"},{"dataSolicitacao":"2044","codigoEPI":"60014562","descricaoEPI":"CA43174 - LUVA PARA PROTECAO CONTRA AGENTES QUIMICOS TAMANHO 8 (M)","codigoMatricula":"003535","colaborador":"MAIRA HILIAN LOPES","dataEntrega":"20231005","horaEntrega":"08:43:10","quantidadeEntregue":"3"},{"dataSolicitacao":"2044","codigoEPI":"60014561","descricaoEPI":"CA43174 - LUVA PARA PROTECAO CONTRA AGENTES QUIMICOS TAMANHO 7 (P)","codigoMatricula":"003594","colaborador":"MAGDA FREITAS RIBEIRO","dataEntrega":"20231005","horaEntrega":"07:50:13","quantidadeEntregue":"2"},{"dataSolicitacao":"2044","codigoEPI":"60014562","descricaoEPI":"CA43174 - LUVA PARA PROTECAO CONTRA AGENTES QUIMICOS TAMANHO 8 (M)","codigoMatricula":"002655","colaborador":"CAROLINE SILVEIRA MATOZO","dataEntrega":"20231004","horaEntrega":"07:39:33","quantidadeEntregue":"2"},{"dataSolicitacao":"2044","codigoEPI":"60014561","descricaoEPI":"CA43174 - LUVA PARA PROTECAO CONTRA AGENTES QUIMICOS TAMANHO 7 (P)","codigoMatricula":"003602","colaborador":"ANA CAROLINA SOUZA ROSSALES","dataEntrega":"20231005","horaEntrega":"11:36:36","quantidadeEntregue":"1"},{"dataSolicitacao":"2044","codigoEPI":"60014561","descricaoEPI":"CA43174 - LUVA PARA PROTECAO CONTRA AGENTES QUIMICOS TAMANHO 7 (P)","codigoMatricula":"001597","colaborador":"RAQUEL NORNBERG OLIVEIRA","dataEntrega":"20231003","horaEntrega":"07:57:23","quantidadeEntregue":"3"},{"dataSolicitacao":"2044","codigoEPI":"60014562","descricaoEPI":"CA43174 - LUVA PARA PROTECAO CONTRA AGENTES QUIMICOS TAMANHO 8 (M)","codigoMatricula":"001552","colaborador":"CELINA MARES DUARTE FAGUNDES","dataEntrega":"20230923","horaEntrega":"12:40:04","quantidadeEntregue":"2"},{"dataSolicitacao":"2044","codigoEPI":"60014561","descricaoEPI":"CA43174 - LUVA PARA PROTECAO CONTRA AGENTES QUIMICOS TAMANHO 7 (P)","codigoMatricula":"003678","colaborador":"NICOLE DA SILVA RODRIGUES","dataEntrega":"20231005","horaEntrega":"08:02:53","quantidadeEntregue":"3"},{"dataSolicitacao":"2044","codigoEPI":"60014561","descricaoEPI":"CA43174 - LUVA PARA PROTECAO CONTRA AGENTES QUIMICOS TAMANHO 7 (P)","codigoMatricula":"001139","colaborador":"SILVANIA FERREIRA","dataEntrega":"20230923","horaEntrega":"09:01:02","quantidadeEntregue":"1"},{"dataSolicitacao":"2044","codigoEPI":"60014562","descricaoEPI":"CA43174 - LUVA PARA PROTECAO CONTRA AGENTES QUIMICOS TAMANHO 8 (M)","codigoMatricula":"003237","colaborador":"RAQUEL VILELLA FARIAS","dataEntrega":"20231005","horaEntrega":"07:04:08","quantidadeEntregue":"3"},{"dataSolicitacao":"2044","codigoEPI":"60014561","descricaoEPI":"CA43174 - LUVA PARA PROTECAO CONTRA AGENTES QUIMICOS TAMANHO 7 (P)","codigoMatricula":"002575","colaborador":"ANA PAULA DE MELO ISLABAO","dataEntrega":"20231003","horaEntrega":"07:59:52","quantidadeEntregue":"3"},{"dataSolicitacao":"2044","codigoEPI":"60014561","descricaoEPI":"CA43174 - LUVA PARA PROTECAO CONTRA AGENTES QUIMICOS TAMANHO 7 (P)","codigoMatricula":"003546","colaborador":"FRANCIELE DA SILVEIRA GOETZKE LEDEBUHR","dataEntrega":"20231004","horaEntrega":"14:22:17","quantidadeEntregue":"2"},{"dataSolicitacao":"2044","codigoEPI":"60014562","descricaoEPI":"CA43174 - LUVA PARA PROTECAO CONTRA AGENTES QUIMICOS TAMANHO 8 (M)","codigoMatricula":"001307","colaborador":"BIANE MOTA DA SILVA","dataEntrega":"20231010","horaEntrega":"08:49:01","quantidadeEntregue":"4"},{"dataSolicitacao":"2044","codigoEPI":"60014561","descricaoEPI":"CA43174 - LUVA PARA PROTECAO CONTRA AGENTES QUIMICOS TAMANHO 7 (P)","codigoMatricula":"003034","colaborador":"VANESSA FERNADES MACHADO","dataEntrega":"20231005","horaEntrega":"11:35:22","quantidadeEntregue":"2"},{"dataSolicitacao":"2044","codigoEPI":"60014561","descricaoEPI":"CA43174 - LUVA PARA PROTECAO CONTRA AGENTES QUIMICOS TAMANHO 7 (P)","codigoMatricula":"003528","colaborador":"EMILLY MULLER DE ALMEIDA","dataEntrega":"20231004","horaEntrega":"08:44:13","quantidadeEntregue":"6"},{"dataSolicitacao":"2044","codigoEPI":"60014561","descricaoEPI":"CA43174 - LUVA PARA PROTECAO CONTRA AGENTES QUIMICOS TAMANHO 7 (P)","codigoMatricula":"003530","colaborador":"KETLYN ROSARIO LEAL","dataEntrega":"20231005","horaEntrega":"12:22:03","quantidadeEntregue":"1"},{"dataSolicitacao":"2044","codigoEPI":"60014561","descricaoEPI":"CA43174 - LUVA PARA PROTECAO CONTRA AGENTES QUIMICOS TAMANHO 7 (P)","codigoMatricula":"003666","colaborador":"VIVIANA CARDOSO DIETRICH","dataEntrega":"20231003","horaEntrega":"08:42:43","quantidadeEntregue":"3"},{"dataSolicitacao":"2044","codigoEPI":"60014561","descricaoEPI":"CA43174 - LUVA PARA PROTECAO CONTRA AGENTES QUIMICOS TAMANHO 7 (P)","codigoMatricula":"002523","colaborador":"CRISTIANE RAMOS ALVES","dataEntrega":"20230921","horaEntrega":"06:19:40","quantidadeEntregue":"1"},{"dataSolicitacao":"2044","codigoEPI":"60014561","descricaoEPI":"CA43174 - LUVA PARA PROTECAO CONTRA AGENTES QUIMICOS TAMANHO 7 (P)","codigoMatricula":"003538","colaborador":"KAMILA SOARES DE BARROS","dataEntrega":"20230930","horaEntrega":"10:41:24","quantidadeEntregue":"2"},{"dataSolicitacao":"2044","codigoEPI":"60014562","descricaoEPI":"CA43174 - LUVA PARA PROTECAO CONTRA AGENTES QUIMICOS TAMANHO 8 (M)","codigoMatricula":"003598","colaborador":"LUBIA LIMA DA SILVA","dataEntrega":"20231005","horaEntrega":"08:44:07","quantidadeEntregue":"3"},{"dataSolicitacao":"2044","codigoEPI":"60014561","descricaoEPI":"CA43174 - LUVA PARA PROTECAO CONTRA AGENTES QUIMICOS TAMANHO 7 (P)","codigoMatricula":"002731","colaborador":"TALITA KOHLS KLUMB GUILHERME","dataEntrega":"20231005","horaEntrega":"07:42:37","quantidadeEntregue":"3"},{"dataSolicitacao":"2044","codigoEPI":"60014561","descricaoEPI":"CA43174 - LUVA PARA PROTECAO CONTRA AGENTES QUIMICOS TAMANHO 7 (P)","codigoMatricula":"003643","colaborador":"KAYLANE SOUZA BENTO","dataEntrega":"20231005","horaEntrega":"14:16:31","quantidadeEntregue":"2"},{"dataSolicitacao":"2044","codigoEPI":"60014561","descricaoEPI":"CA43174 - LUVA PARA PROTECAO CONTRA AGENTES QUIMICOS TAMANHO 7 (P)","codigoMatricula":"003651","colaborador":"NATIELE DOS SANTOS WEIKAMP","dataEntrega":"20231005","horaEntrega":"14:19:05","quantidadeEntregue":"2"},{"dataSolicitacao":"2044","codigoEPI":"60014561","descricaoEPI":"CA43174 - LUVA PARA PROTECAO CONTRA AGENTES QUIMICOS TAMANHO 7 (P)","codigoMatricula":"003647","colaborador":"FRANCIELE ROCHA SILVEIRA","dataEntrega":"20231005","horaEntrega":"14:24:03","quantidadeEntregue":"3"},{"dataSolicitacao":"2044","codigoEPI":"60014561","descricaoEPI":"CA43174 - LUVA PARA PROTECAO CONTRA AGENTES QUIMICOS TAMANHO 7 (P)","codigoMatricula":"003664","colaborador":"BIANCA BORGES MARTINS","dataEntrega":"20231005","horaEntrega":"14:07:52","quantidadeEntregue":"2"},{"dataSolicitacao":"2044","codigoEPI":"60014561","descricaoEPI":"CA43174 - LUVA PARA PROTECAO CONTRA AGENTES QUIMICOS TAMANHO 7 (P)","codigoMatricula":"003612","colaborador":"SIMONE CANTOS DE ARAUJO","dataEntrega":"20231003","horaEntrega":"12:25:09","quantidadeEntregue":"1"},{"dataSolicitacao":"2044","codigoEPI":"60014561","descricaoEPI":"CA43174 - LUVA PARA PROTECAO CONTRA AGENTES QUIMICOS TAMANHO 7 (P)","codigoMatricula":"003601","colaborador":"TOCHIE KIMURA","dataEntrega":"20231005","horaEntrega":"07:41:42","quantidadeEntregue":"1"},{"dataSolicitacao":"2044","codigoEPI":"60014562","descricaoEPI":"CA43174 - LUVA PARA PROTECAO CONTRA AGENTES QUIMICOS TAMANHO 8 (M)","codigoMatricula":"003641","colaborador":"BRUNA NUNES LESSA","dataEntrega":"20231005","horaEntrega":"11:40:18","quantidadeEntregue":"3"},{"dataSolicitacao":"2044","codigoEPI":"60014561","descricaoEPI":"CA43174 - LUVA PARA PROTECAO CONTRA AGENTES QUIMICOS TAMANHO 7 (P)","codigoMatricula":"002877","colaborador":"VANESSA GOUVEA DE OLIVEIRA","dataEntrega":"20231004","horaEntrega":"14:04:26","quantidadeEntregue":"1"},{"dataSolicitacao":"2044","codigoEPI":"60014561","descricaoEPI":"CA43174 - LUVA PARA PROTECAO CONTRA AGENTES QUIMICOS TAMANHO 7 (P)","codigoMatricula":"002400","colaborador":"NARA LUCIA MENDES OLACHEA","dataEntrega":"20230923","horaEntrega":"14:35:52","quantidadeEntregue":"3"},{"dataSolicitacao":"2044","codigoEPI":"60014561","descricaoEPI":"CA43174 - LUVA PARA PROTECAO CONTRA AGENTES QUIMICOS TAMANHO 7 (P)","codigoMatricula":"003537","colaborador":"PATRICIA BORBA DE VARGAS","dataEntrega":"20231007","horaEntrega":"09:06:51","quantidadeEntregue":"2"},{"dataSolicitacao":"2044","codigoEPI":"60014562","descricaoEPI":"CA43174 - LUVA PARA PROTECAO CONTRA AGENTES QUIMICOS TAMANHO 8 (M)","codigoMatricula":"003652","colaborador":"DIELE ROJAHN DOS SANTOS","dataEntrega":"20231005","horaEntrega":"12:23:08","quantidadeEntregue":"3"},{"dataSolicitacao":"2044","codigoEPI":"60014562","descricaoEPI":"CA43174 - LUVA PARA PROTECAO CONTRA AGENTES QUIMICOS TAMANHO 8 (M)","codigoMatricula":"003661","colaborador":"JENNIFER SILVA DOS SANTOS","dataEntrega":"20231004","horaEntrega":"08:25:22","quantidadeEntregue":"3"},{"dataSolicitacao":"2044","codigoEPI":"60014562","descricaoEPI":"CA43174 - LUVA PARA PROTECAO CONTRA AGENTES QUIMICOS TAMANHO 8 (M)","codigoMatricula":"003008","colaborador":"CATIA REGINA SANTOS DE SOUZA","dataEntrega":"20231005","horaEntrega":"07:49:10","quantidadeEntregue":"3"},{"dataSolicitacao":"2044","codigoEPI":"60014561","descricaoEPI":"CA43174 - LUVA PARA PROTECAO CONTRA AGENTES QUIMICOS TAMANHO 7 (P)","codigoMatricula":"003589","colaborador":"KEROLAINE MORAES FERREIRA","dataEntrega":"20231003","horaEntrega":"11:09:47","quantidadeEntregue":"3"},{"dataSolicitacao":"2044","codigoEPI":"60014562","descricaoEPI":"CA43174 - LUVA PARA PROTECAO CONTRA AGENTES QUIMICOS TAMANHO 8 (M)","codigoMatricula":"003607","colaborador":"RENATA MACHADO DOS SANTOS","dataEntrega":"20231004","horaEntrega":"08:30:33","quantidadeEntregue":"3"},{"dataSolicitacao":"2044","codigoEPI":"60014562","descricaoEPI":"CA43174 - LUVA PARA PROTECAO CONTRA AGENTES QUIMICOS TAMANHO 8 (M)","codigoMatricula":"003649","colaborador":"SHAIANE DA SILVA","dataEntrega":"20231004","horaEntrega":"11:55:15","quantidadeEntregue":"3"},{"dataSolicitacao":"2044","codigoEPI":"60014561","descricaoEPI":"CA43174 - LUVA PARA PROTECAO CONTRA AGENTES QUIMICOS TAMANHO 7 (P)","codigoMatricula":"003564","colaborador":"KARINA FURTADO RADMANN","dataEntrega":"20231005","horaEntrega":"14:23:30","quantidadeEntregue":"3"},{"dataSolicitacao":"2044","codigoEPI":"60014562","descricaoEPI":"CA43174 - LUVA PARA PROTECAO CONTRA AGENTES QUIMICOS TAMANHO 8 (M)","codigoMatricula":"003015","colaborador":"MIRIAN LANE PINTO DA SILVA","dataEntrega":"20231004","horaEntrega":"07:20:54","quantidadeEntregue":"3"},{"dataSolicitacao":"2044","codigoEPI":"60014561","descricaoEPI":"CA43174 - LUVA PARA PROTECAO CONTRA AGENTES QUIMICOS TAMANHO 7 (P)","codigoMatricula":"002980","colaborador":"EDUARDA VICENTINE CARDOSO","dataEntrega":"20231004","horaEntrega":"11:55:51","quantidadeEntregue":"3"},{"dataSolicitacao":"2044","codigoEPI":"60014561","descricaoEPI":"CA43174 - LUVA PARA PROTECAO CONTRA AGENTES QUIMICOS TAMANHO 7 (P)","codigoMatricula":"003663","colaborador":"EDILAINE ULGUIM DILLMANN","dataEntrega":"20231005","horaEntrega":"13:01:28","quantidadeEntregue":"3"},{"dataSolicitacao":"2044","codigoEPI":"60014561","descricaoEPI":"CA43174 - LUVA PARA PROTECAO CONTRA AGENTES QUIMICOS TAMANHO 7 (P)","codigoMatricula":"003034","colaborador":"VANESSA FERNADES MACHADO","dataEntrega":"20231005","horaEntrega":"11:35:22","quantidadeEntregue":"2"},{"dataSolicitacao":"2044","codigoEPI":"60014561","descricaoEPI":"CA43174 - LUVA PARA PROTECAO CONTRA AGENTES QUIMICOS TAMANHO 7 (P)","codigoMatricula":"002733","colaborador":"PRISCILA NUNES RODRIGUES","dataEntrega":"20231003","horaEntrega":"08:08:01","quantidadeEntregue":"3"},{"dataSolicitacao":"2044","codigoEPI":"60014561","descricaoEPI":"CA43174 - LUVA PARA PROTECAO CONTRA AGENTES QUIMICOS TAMANHO 7 (P)","codigoMatricula":"003527","colaborador":"CHARLENE SARAIVA LOPES","dataEntrega":"20231003","horaEntrega":"08:45:15","quantidadeEntregue":"4"},{"dataSolicitacao":"2044","codigoEPI":"60014562","descricaoEPI":"CA43174 - LUVA PARA PROTECAO CONTRA AGENTES QUIMICOS TAMANHO 8 (M)","codigoMatricula":"002510","colaborador":"LUCIANA DA SILVA SOARES","dataEntrega":"20230921","horaEntrega":"22:47:56","quantidadeEntregue":"1"},{"dataSolicitacao":"2044","codigoEPI":"60014562","descricaoEPI":"CA43174 - LUVA PARA PROTECAO CONTRA AGENTES QUIMICOS TAMANHO 8 (M)","codigoMatricula":"002687","colaborador":"CAROLINA KIRST LOPES","dataEntrega":"20231004","horaEntrega":"13:57:29","quantidadeEntregue":"5"},{"dataSolicitacao":"2044","codigoEPI":"60014562","descricaoEPI":"CA43174 - LUVA PARA PROTECAO CONTRA AGENTES QUIMICOS TAMANHO 8 (M)","codigoMatricula":"002609","colaborador":"SIMONE CASTRO DOS SANTOS SOARES","dataEntrega":"20231004","horaEntrega":"13:01:39","quantidadeEntregue":"3"},{"dataSolicitacao":"2044","codigoEPI":"60014561","descricaoEPI":"CA43174 - LUVA PARA PROTECAO CONTRA AGENTES QUIMICOS TAMANHO 7 (P)","codigoMatricula":"003252","colaborador":"THAIS NUNES DUARTE","dataEntrega":"20231003","horaEntrega":"14:19:34","quantidadeEntregue":"3"},{"dataSolicitacao":"2044","codigoEPI":"60014561","descricaoEPI":"CA43174 - LUVA PARA PROTECAO CONTRA AGENTES QUIMICOS TAMANHO 7 (P)","codigoMatricula":"002730","colaborador":"RITIELE SEVERO NUNES","dataEntrega":"20231003","horaEntrega":"14:20:10","quantidadeEntregue":"2"},{"dataSolicitacao":"2044","codigoEPI":"60014561","descricaoEPI":"CA43174 - LUVA PARA PROTECAO CONTRA AGENTES QUIMICOS TAMANHO 7 (P)","codigoMatricula":"003054","colaborador":"MARTA ROSA FERNANDES","dataEntrega":"20231005","horaEntrega":"14:22:34","quantidadeEntregue":"3"},{"dataSolicitacao":"2044","codigoEPI":"60014561","descricaoEPI":"CA43174 - LUVA PARA PROTECAO CONTRA AGENTES QUIMICOS TAMANHO 7 (P)","codigoMatricula":"002710","colaborador":"PRISCILA BAAD BUDZIARECK","dataEntrega":"20231005","horaEntrega":"14:08:31","quantidadeEntregue":"3"},{"dataSolicitacao":"2044","codigoEPI":"60014562","descricaoEPI":"CA43174 - LUVA PARA PROTECAO CONTRA AGENTES QUIMICOS TAMANHO 8 (M)","codigoMatricula":"003650","colaborador":"SAMANTHA COLVARA ESMERIO","dataEntrega":"20231005","horaEntrega":"14:17:42","quantidadeEntregue":"3"},{"dataSolicitacao":"2044","codigoEPI":"60014561","descricaoEPI":"CA43174 - LUVA PARA PROTECAO CONTRA AGENTES QUIMICOS TAMANHO 7 (P)","codigoMatricula":"003374","colaborador":"VALESCA RODRIGUES DIAS","dataEntrega":"20231003","horaEntrega":"14:01:37","quantidadeEntregue":"3"},{"dataSolicitacao":"2044","codigoEPI":"60014561","descricaoEPI":"CA43174 - LUVA PARA PROTECAO CONTRA AGENTES QUIMICOS TAMANHO 7 (P)","codigoMatricula":"003547","colaborador":"DIULIENE FREITAS DOS SANTOS","dataEntrega":"20231010","horaEntrega":"14:24:03","quantidadeEntregue":"7"},{"dataSolicitacao":"2044","codigoEPI":"60014561","descricaoEPI":"CA43174 - LUVA PARA PROTECAO CONTRA AGENTES QUIMICOS TAMANHO 7 (P)","codigoMatricula":"003591","colaborador":"TAUANA LACERDA EINHARDT","dataEntrega":"20231004","horaEntrega":"11:07:56","quantidadeEntregue":"1"},{"dataSolicitacao":"2044","codigoEPI":"60014562","descricaoEPI":"CA43174 - LUVA PARA PROTECAO CONTRA AGENTES QUIMICOS TAMANHO 8 (M)","codigoMatricula":"003540","colaborador":"LEONARDO DAMASCENO DOS SANTOS","dataEntrega":"20231004","horaEntrega":"11:06:35","quantidadeEntregue":"4"},{"dataSolicitacao":"2044","codigoEPI":"60014561","descricaoEPI":"CA43174 - LUVA PARA PROTECAO CONTRA AGENTES QUIMICOS TAMANHO 7 (P)","codigoMatricula":"003136","colaborador":"PAULO ROBERTO NUNES DA ROSA","dataEntrega":"20231011","horaEntrega":"16:07:57","quantidadeEntregue":"1"},{"dataSolicitacao":"2044","codigoEPI":"60014562","descricaoEPI":"CA43174 - LUVA PARA PROTECAO CONTRA AGENTES QUIMICOS TAMANHO 8 (M)","codigoMatricula":"003136","colaborador":"PAULO ROBERTO NUNES DA ROSA","dataEntrega":"20231011","horaEntrega":"16:10:12","quantidadeEntregue":"1"},{"dataSolicitacao":"2044","codigoEPI":"60014561","descricaoEPI":"CA43174 - LUVA PARA PROTECAO CONTRA AGENTES QUIMICOS TAMANHO 7 (P)","codigoMatricula":"003136","colaborador":"PAULO ROBERTO NUNES DA ROSA","dataEntrega":"20231011","horaEntrega":"16:19:50","quantidadeEntregue":"1"},{"dataSolicitacao":"2044","codigoEPI":"60014561","descricaoEPI":"CA43174 - LUVA PARA PROTECAO CONTRA AGENTES QUIMICOS TAMANHO 7 (P)","codigoMatricula":"003136","colaborador":"PAULO ROBERTO NUNES DA ROSA","dataEntrega":"20231011","horaEntrega":"16:19:50","quantidadeEntregue":"1"}]